[
  {
    "DataSetName": "default.cds",
    "IsSampleData": false,
    "IsWritable": false,
    "LogicalName": "cat_ProcessDesignerLoc",
    "Name": "ProcessDesignerLoc",
    "Schema": "![ApprovalTxt:s, CancelTxt:s, Close:s, False:s, PublishTxt:s, RefreshTxt:s, SaveTxt:s, True:s, addedApproversTrace:s, cnfrmDialogDeleteAppDataMsg:s, cnfrmDialogDeleteDeactivateProcess:s, cnfrmDialogDeleteStgMsg:s, cnfrmDialogNodeBusyMsg:s, cnvsComLblStgCondnTxt:s, cnvsCompAddNode:s, cnvsCompDeleteNode:s, cnvsCompIcoFirstFalseNodeTooltipT1:s, cnvsCompIcoFirstFalseNodeTooltipT2:s, cnvsCompIcoFirstTrueNodeTooltipT1:s, cnvsCompIcoFirstTrueNodeTooltipT2:s, cnvsCompIcoFirstTrueNodeTooltipT3:s, cnvsCompInfoBtnContent:s, cnvsCompLblFalse:s, cnvsCompLblNoNodeInStg:s, cnvsCompLblStage:s, cnvsCompProcessDesingerTxt:s, cnvsCompStgCmdBarDelete:s, cnvsCompStgCmdBarEdit:s, cnvsCompStgCmdBarMoveDown:s, cnvsCompStgCmdBarMoveUp:s, cnvsCompTrue:s, fluentPnlDynmicApprovr:s, fluentPnlOnSaveSavingNode:s, fluentPnlOnSaveSavingStg:s, fluentPnlOnSaveUpdatingCondns:s, fluentPnlPublishMsg:s, fluentPnlTrcMsgNewlyAddedApprovr:s, fluentPnlTrcMsgRemovedApprovr:s, iconAddStgTooltip:s, iconBckToolTip:s, lblDelete:s, lblNoStage:s, mainCmdBarVariable:s, mainCmdBarVersions:s, nodeContApproverHintText:s, nodeContApproverSearchTermToShortMsg:s, nodeContApproverSuggestionsHeader:s, nodeContBtnAddUser:s, nodeContCustomResponseHintText:s, nodeContLblApprovalConfigText:s, nodeContLblApprovalType:s, nodeContLblCustomResponses:s, nodeContLblDelegationRule:s, nodeContLblDelegationRuleDesc:s, nodeContLblDescription:s, nodeContLblNodeApprover:s, nodeContLblNodeName:s, nodeContLblNotification:s, nodeContLblTimeOut:s, nodeContLblTimeoutDescription:s, nodeContNoReqDataFieldFound:s, nodeContNoResultFoundMsg:s, nodeContNodeType:s, nodeDeleteText2:s, nodePanelHeaderEditTxt:s, nodePanelHeaderTxt:s, nodeRuContainerBtnReset:s, nodeRuContainerBtnResetEdit:s, nodeRuContainerLblCondTarget:s, nodeRuContainerLblGoToStage:s, nodeRuContainerLblNodeCondition:s, nodeRuContainerLblNodeDescription:s, nodeRuContainerLblNodeName:s, nodeRuContainerLblNodeOperand:s, nodeRuContainerLblNodeType:s, nodeRuContainerLblRequestData:s, nodeRuContainerLblRequestDataEmpty:s, nodeRuContainerLblReset:s, nodeRuContainerLblSource:s, nodeRuContainerLblTargetReqDataT1:s, nodeRuContainerLblTargetReqDataT2:s, nodeRuContainerLblTargetReqDataT3:s, processDefaultName:s, processSaveMsg:s, pubContLblPublishVerInfoDateFormat:s, pubContainerBtnPublish:s, pubContainerLblActivateOnPublish:s, pubContainerLblPublishInfo:s, pubContainerLblVersionInfoFirstPublish:s, pubContainerLblVersionInfoVersionText1:s, pubContainerLblVersionInfoVersionText2:s, pubContainerLblVersionInfoVersionText3:s, pubContainerProgressIndicatorText:s, pubContainerTglActivateFalseText:s, pubContainerTglActivateTrueText:s, removedApproversTrace:s, scrOnVisLoadMsg:s, scrOnVisValidtionCheck1:s, scrOnVisValidtionCheck2:s, scrOnVisValidtionCheck3:s, scrOnVisValidtionCheck4:s, stagePanelHeaderEditTxt:s, stagePanelHeaderTxt:s, stgContBtnReset:s, stgContBtnResetEditText:s, stgContDdlReqDataCondAccLblTxt:s, stgContDdlStgCondnSourceTxt:s, stgContDdlStgCondnTxt:s, stgContFirstStgNoCondition:s, stgContLabelParallelCond:s, stgContLblCondTargetT1:s, stgContLblCondTargetT2:s, stgContLblCondition:s, stgContLblEqual:s, stgContLblIsPrallelTooltip:s, stgContLblRequestData:s, stgContLblRequestDataDetailsT1:s, stgContLblRequestDataDetailsT2:s, stgContLblRequstDataEmpty:s, stgContLblSource:s, stgContLblStageHasDependancy:s, stgContLblStgCondnHeader:s, stgContLblStgDescription:s, stgContLblStgName:s, stgContLblStgOperand:s, stgContLblSwitchPaths:s, stgContLblTargetReqDataFoundT1:s, stgContLblTargetReqDataFoundT2:s, stgContLblTargetReqDataFoundT3:s, stgContSwitchLblDefault:s, stgContTblStgDepsCondition:s, stgContTblStgDepsNode:s, stgContTblStgDepsStage:s, stgContTxtLblInfo:s, stgContTxtStgDescPlaceholder:s, stgContTxtStgNamePlaceholder:s, stgDeleteText2:s, tglModernDesignerLbl:s, varContBtnCancelEditTooltip:s, varContBtnSaveAppDataDateFormat:s, varContIcoClearDefaultTooltip:s, varContainerAppDataDeleteBusyMessage:s, varContainerAppDataDeleteDependancyError:s, varContainerAppDataDeleteDependentNode:s, varContainerAppDataDeleteDependentStage:s, varContainerBtnSaveAppDataAddText:s, varContainerBtnSaveAppDataTooltip:s, varContainerBtnSaveAppDataUpdateText:s, varContainerCancelEditVarText:s, varContainerDeleteIconToolttipText:s, varContainerDeleteVariableTextPostfix:s, varContainerDeleteVariableTextPrefix:s, varContainerEditIconTooltipText:s, varContainerLblAppDataDescriptionText:s, varContainerLblAppDataHeaderText:s, varContainerLblProcessNotSavedText:s, varContainerSaveAppDataVariableExistsText:s, varContainerTblHeaderDataType:s, varContainerTblHeaderDefaultValue:s, varContainerTblHeaderDescription:s, varContainerTblHeaderFieldName:s, varPanelHeaderTxt:s, verContLblVersionCreatedOnDateFormat:s, verContainerBtnActivateText:s, verContainerLblNoPublishVersion:s, verContainerPublishText:s, verContainerRefreshText:s, verContainerTableHeaderActivationStatus:s, verContainerTableHeaderCreatedBy:s, verContainerTableHeaderCreatedOn:s, verContainerTableHeaderPublishingStatus:s, verContainerTableHeaderVersion:s, verContainerVersionTitle:s]",
    "Type": "WebResourceInfo"
  }
]